generic/__init__.py
generic/event.py
generic/multidispatch.py
generic/multimethod.py
generic/registry.py
generic-1.1.6.dist-info/LICENSES/BSD-3-Clause.txt
generic-1.1.6.dist-info/METADATA
generic-1.1.6.dist-info/WHEEL
generic-1.1.6.dist-info/RECORD
