Metadata-Version: 2.3
Name: generic
Version: 1.1.6
Summary: Generic programming library for Python
Keywords: generic,multi dispatch,dispatch,event
Author: Andrey Popp
Author-email: 8mayday@gmail.com
Maintainer: Arjan Molenaar
Maintainer-email: gaphor@gmail.com
Requires-Python: >=3.9
Classifier: Development Status :: 5 - Production/Stable
Classifier: Intended Audience :: Developers
Classifier: Intended Audience :: Information Technology
Classifier: License :: OSI Approved :: BSD License
Classifier: Programming Language :: Python
Requires-Dist: exceptiongroup (>=1.0.0) ; python_version < "3.11"
Project-URL: Documentation, https://generic.readthedocs.io/
Project-URL: Homepage, https://generic.readthedocs.io/
Project-URL: Repository, https://github.com/gaphor/generic
